kytool/__init__.py
kytool/adapters/__init__.py
kytool/adapters/repository.py
kytool/bootstrap.py
kytool/di.py
kytool/domain/__init__.py
kytool/domain/base.py
kytool/domain/commands.py
kytool/domain/events.py
kytool/domain/exceptions.py
kytool/entrypoints/__init__.py
kytool/factories.py
kytool/py.typed
kytool/service_layer/__init__.py
kytool/service_layer/handlers.py
kytool/service_layer/messagebus.py
kytool/service_layer/unit_of_work/__init__.py
kytool/service_layer/unit_of_work/fake.py
kytool/service_layer/unit_of_work/in_memory.py
kytool/service_layer/unit_of_work/interfaces.py
kytool-0.5.2.dist-info/LICENSE
kytool-0.5.2.dist-info/METADATA
kytool-0.5.2.dist-info/WHEEL
kytool-0.5.2.dist-info/RECORD
