Metadata-Version: 2.1
Name: kytool
Version: 0.5.2
Summary: Kytool is a tool for creatng
License: MIT
Author: Dmytro Maior
Author-email: mayor4090@gmail.com
Requires-Python: >=3.11,<4.0
Classifier: License :: OSI Approved :: MIT License
Classifier: Programming Language :: Python :: 3
Classifier: Programming Language :: Python :: 3.11
Classifier: Programming Language :: Python :: 3.12
Requires-Dist: decorator (>=5.1.1,<6.0.0)
